README.md
setup.cfg
setup.py
mlnd_test_distributions/Binomialdistribution.py
mlnd_test_distributions/Gaussiandistribution.py
mlnd_test_distributions/Generaldistribution.py
mlnd_test_distributions/__init__.py
mlnd_test_distributions.egg-info/PKG-INFO
mlnd_test_distributions.egg-info/SOURCES.txt
mlnd_test_distributions.egg-info/dependency_links.txt
mlnd_test_distributions.egg-info/not-zip-safe
mlnd_test_distributions.egg-info/top_level.txt