Metadata-Version: 1.0
Name: mlnd-test-distributions
Version: 0.1
Summary: Gaussian distributions
Home-page: UNKNOWN
Author: UNKNOWN
Author-email: bousejin@gmail.com
License: UNKNOWN
Platform: UNKNOWN
